invaders.py
invaderclone/__init__.py
invaderclone/actor.py
invaderclone/bullets.py
invaderclone/burst_shot_powerup.py
invaderclone/constants.py
invaderclone/enemy.py
invaderclone/event_actor.py
invaderclone/explosion.py
invaderclone/game.py
invaderclone/game_over_scene.py
invaderclone/leaderboard.py
invaderclone/leaderboard_scene.py
invaderclone/level0.py
invaderclone/level0_player.py
invaderclone/obstacle.py
invaderclone/playable_actor_physmove.py
invaderclone/playable_actor_simplemove.py
invaderclone/player.py
invaderclone/polygon_title_scene.py
invaderclone/press_any_key_to_exit_scene.py
invaderclone/rgbcolors.py
invaderclone/scene.py
invaderclone/theme.py
invaderclone/data/curs.ttf
invaderclone/data/missing.png
invaderclone/data/missing.wav
invaderclone/data/themes/default/bgm/Credits.txt
invaderclone/data/themes/default/bgm/game.ogg
invaderclone/data/themes/default/bgm/game_over.ogg
invaderclone/data/themes/default/bgm/leaderboard.ogg
invaderclone/data/themes/default/bgm/title.ogg
invaderclone/data/themes/default/bgs/Credits.txt
invaderclone/data/themes/default/bgs/explode+kitty.ogg
invaderclone/data/themes/default/bgs/explode.ogg
invaderclone/data/themes/default/fonts/Credits.txt
invaderclone/data/themes/default/fonts/other.ttf
invaderclone/data/themes/default/fonts/title.ttf
invaderclone/data/themes/default/images/asteroid1.png
invaderclone/data/themes/default/images/asteroid2.png
invaderclone/data/themes/default/images/badbullet.png
invaderclone/data/themes/default/images/burst.png
invaderclone/data/themes/default/images/enemy1.png
invaderclone/data/themes/default/images/enemy2.png
invaderclone/data/themes/default/images/enemy3.png
invaderclone/data/themes/default/images/explosion.png
invaderclone/data/themes/default/images/gameover.png
invaderclone/data/themes/default/images/goodbullet.png
invaderclone/data/themes/default/images/hero.png
invaderclone/data/themes/default/images/logo.png
invaderclone/data/themes/default/images/obstacle1.png
invaderclone-1.0.0.dist-info/METADATA
invaderclone-1.0.0.dist-info/WHEEL
invaderclone-1.0.0.dist-info/entry_points.txt
invaderclone-1.0.0.dist-info/top_level.txt
invaderclone-1.0.0.dist-info/RECORD
