Metadata-Version: 2.1
Name: invaderclone
Version: 1.0.0
Summary: A module Space Invaders clone in Python Pygame
Home-page: https://github.com/ganelonhb/invaderclone
Author: Zachary Worcester
Author-email: zworcester0@csu.fullerton.edu
Requires-Python: >=3.5.0
Requires-Dist: pygame
